MANIFEST.in
README.md
build.py
requirements.txt
setup.py
data_place.egg-info/PKG-INFO
data_place.egg-info/SOURCES.txt
data_place.egg-info/dependency_links.txt
data_place.egg-info/requires.txt
data_place.egg-info/top_level.txt
dataplace/__init__.py
dataplace/base.py
dataplace/callback.py
dataplace/control.py
dataplace/handler.py
dataplace/io.py
dataplace/receive.py
dataplace/send.py
dataplace/store.py