Metadata-Version: 2.1
Name: data-place
Version: 0.2.0
Summary: A powerfull and flexible framework for designing async socket based data streaming and distribution systems, with automated parsing, dynamic data store and high-level control hooks.
Home-page: https://github.com/Shahaf-F-S/data-place
Author: Shahaf Frank-Shapir
Author-email: shahaffrs@gmail.com
License: MIT
Classifier: Intended Audience :: Developers
Classifier: License :: OSI Approved :: MIT License
Classifier: Programming Language :: Python
Classifier: Programming Language :: Python :: 3
Classifier: Programming Language :: Python :: 3.8
Classifier: Programming Language :: Python :: 3.9
Classifier: Programming Language :: Python :: 3.10
Classifier: Programming Language :: Python :: 3.11
Classifier: Operating System :: OS Independent
Requires-Dist: websockets
Provides-Extra: dev
